{
	"agents": [
		{
			"type": "active",
			"radio": 0.300000,
			"x": -4.583268,
			"y": 4.583003,
			"theta": -1.785486,
			"v0": 0.479852,
			"w0": 0.296173,
			"av": 0.150000,
			"aw": 1.047700,
			"goal": {
				"x": 8.736903,
				"y": -5.317137
			}
		},
		{
			"type": "passive",
			"radio": 0.300000,
			"x": -2.818907,
			"y": 8.650953,
			"theta": 0.170747,
			"v0": 0.381367,
			"w0": 0.096180
		},
		{
			"type": "passive",
			"radio": 0.300000,
			"x": 0.321515,
			"y": 8.217742,
			"theta": 0.840494,
			"v0": 0.245093,
			"w0": 0.000000
		},
		{
			"type": "passive",
			"radio": 0.300000,
			"x": 4.962015,
			"y": -8.107378,
			"theta": 2.509166,
			"v0": 0.331016,
			"w0": 0.000000
		},
		{
			"type": "passive",
			"radio": 0.300000,
			"x": -0.190797,
			"y": 4.886463,
			"theta": -0.978424,
			"v0": 0.179455,
			"w0": 0.000000
		},
		{
			"type": "passive",
			"radio": 0.300000,
			"x": 9.366595,
			"y": 10.463457,
			"theta": -1.354809,
			"v0": 0.395498,
			"w0": 0.086028
		},
		{
			"type": "passive",
			"radio": 0.300000,
			"x": -11.998693,
			"y": -4.902160,
			"theta": -2.242752,
			"v0": 0.215753,
			"w0": 0.000000
		},
		{
			"type": "passive",
			"radio": 0.300000,
			"x": 11.372374,
			"y": -10.240738,
			"theta": 2.564753,
			"v0": 0.313075,
			"w0": 0.000000
		},
		{
			"type": "passive",
			"radio": 0.300000,
			"x": 6.345810,
			"y": -7.120159,
			"theta": 1.079472,
			"v0": 0.156646,
			"w0": 0.000000
		},
		{
			"type": "passive",
			"radio": 0.300000,
			"x": 3.601157,
			"y": 10.583620,
			"theta": -1.131124,
			"v0": 0.324010,
			"w0": 0.051504
		},
		{
			"type": "passive",
			"radio": 0.300000,
			"x": -1.199487,
			"y": -3.065562,
			"theta": -1.119302,
			"v0": 0.277832,
			"w0": 0.000000
		},
		{
			"type": "passive",
			"radio": 0.300000,
			"x": -3.496822,
			"y": -1.792216,
			"theta": -1.065794,
			"v0": 0.389193,
			"w0": -0.084487
		},
		{
			"type": "passive",
			"radio": 0.300000,
			"x": -9.770663,
			"y": -6.511934,
			"theta": -1.615739,
			"v0": 0.398014,
			"w0": 0.000000
		},
		{
			"type": "passive",
			"radio": 0.300000,
			"x": 3.573601,
			"y": 1.010005,
			"theta": 1.972537,
			"v0": 0.358191,
			"w0": 0.055773
		},
		{
			"type": "passive",
			"radio": 0.300000,
			"x": -5.099013,
			"y": 10.069959,
			"theta": -1.892686,
			"v0": 0.155031,
			"w0": 0.000000
		},
		{
			"type": "passive",
			"radio": 0.300000,
			"x": -10.709763,
			"y": -0.405379,
			"theta": -2.455807,
			"v0": 0.276484,
			"w0": 0.009104
		},
		{
			"type": "passive",
			"radio": 0.300000,
			"x": 9.895116,
			"y": 1.758872,
			"theta": 0.354811,
			"v0": 0.179092,
			"w0": 0.000000
		},
		{
			"type": "passive",
			"radio": 0.300000,
			"x": -9.205918,
			"y": 1.255517,
			"theta": 3.080557,
			"v0": 0.258610,
			"w0": 0.000000
		},
		{
			"type": "passive",
			"radio": 0.300000,
			"x": -11.238865,
			"y": -5.690575,
			"theta": -1.947935,
			"v0": 0.163165,
			"w0": 0.000000
		},
		{
			"type": "passive",
			"radio": 0.300000,
			"x": -0.084207,
			"y": -2.741757,
			"theta": -0.530535,
			"v0": 0.377310,
			"w0": 0.000000
		},
		{
			"type": "passive",
			"radio": 0.300000,
			"x": 2.460407,
			"y": 10.194475,
			"theta": 0.929952,
			"v0": 0.354529,
			"w0": 0.102641
		}
	]
}